langchain_qdrant/__init__.py
langchain_qdrant/_utils.py
langchain_qdrant/fastembed_sparse.py
langchain_qdrant/py.typed
langchain_qdrant/qdrant.py
langchain_qdrant/sparse_embeddings.py
langchain_qdrant/vectorstores.py
gigachain_qdrant-0.1.3.dist-info/LICENSE
gigachain_qdrant-0.1.3.dist-info/METADATA
gigachain_qdrant-0.1.3.dist-info/WHEEL
gigachain_qdrant-0.1.3.dist-info/RECORD
