Metadata-Version: 2.1
Name: gigachain-qdrant
Version: 0.1.3
Summary: An integration package connecting Qdrant and GigaChain
Home-page: https://github.com/ai-forever/gigachain
License: MIT
Requires-Python: >=3.8.1,<4.0
Classifier: License :: OSI Approved :: MIT License
Classifier: Programming Language :: Python :: 3
Classifier: Programming Language :: Python :: 3.9
Classifier: Programming Language :: Python :: 3.10
Classifier: Programming Language :: Python :: 3.11
Classifier: Programming Language :: Python :: 3.12
Provides-Extra: fastembed
Requires-Dist: fastembed (>=0.3.3,<0.4.0) ; (python_full_version >= "3.8.1" and python_version < "3.13") and (extra == "fastembed")
Requires-Dist: gigachain-core (>=0.1.52,<0.3)
Requires-Dist: pydantic (>=2.7.4,<3.0.0)
Requires-Dist: qdrant-client (>=1.10.1,<2.0.0)
Project-URL: Repository, https://github.com/ai-forever/gigachain
Project-URL: Release Notes, https://github.com/ai-forever/gigachain/releases?q=tag%3A%22gigachain-qdrant%3D%3D0%22&expanded=true
Project-URL: Source Code, https://github.com/ai-forever/gigachain/tree/master/libs/partners/qdrant
